pyplotlib/__init__.py
pyplotlib-0.0.56.dist-info/LICENSE
pyplotlib-0.0.56.dist-info/METADATA
pyplotlib-0.0.56.dist-info/WHEEL
pyplotlib-0.0.56.dist-info/top_level.txt
pyplotlib-0.0.56.dist-info/RECORD
