Metadata-Version: 2.1
Name: pyplotlib
Version: 0.0.56
Summary: My short description for my project.
Home-page: https://github.com/franceme/pyplotlib
Author: Miles Frantz
Author-email: frantzme@vt.edu
License: UNKNOWN
Platform: UNKNOWN
Classifier: Programming Language :: Python
Classifier: Programming Language :: Python :: 3
Classifier: Programming Language :: Python :: 3.8
Requires-Python: >=3.8.0
Provides-Extra: all
License-File: LICENSE
